[{"total_degree":134,"questionsData":[{"title":"من تورط من المؤمنين في الإشاعات الكاذبة أقيم عليه حد القذف.","explain_answer":null,"year":2023,"score":1,"article":null,"difficulty_level_name":"مبتدئ","difficulty_level":2,"answers_data":[{"answer1":"صح","is_correct":"true"},{"answer2":"خطأ","is_correct":"false"}]},{"title":"نشر بعض المسلمين للإشاعات الكاذبة دليل على خطورة كيد الشيطان.","explain_answer":"","year":2023,"score":1,"article":null,"difficulty_level_name":"مبتدئ","difficulty_level":2,"answers_data":[{"answer1":"صح","is_correct":"true"},{"answer2":"خطأ","is_correct":"false"}]},{"title":"<p>من أخفى أعماله القبيحة في الدنيا فإن جوارحه يوم القيامة تكون :</p>\r\n","explain_answer":"<p>جوارحهم تكون شاهدة عليهم، ولا تكون منكرة أو ساترة أو نافعة؛ بل شاهدة <u>فاضحة </u>لأعمالهم القبيحة.</p>\r\n","year":2023,"score":2,"article":null,"difficulty_level_name":"مبتدئ","difficulty_level":2,"answers_data":[{"answer1":"<p>منكرة</p>\r\n","is_correct":"false"},{"answer2":"<p>ساترة</p>\r\n","is_correct":"false"},{"answer3":"<p>فاضحة</p>\r\n","is_correct":"true"},{"answer4":"<p>نافعة</p>\r\n","is_correct":"false"}]},{"title":"نجاح الأسرة يتوقف على مدى التوافق بين :","explain_answer":null,"year":2023,"score":2,"article":null,"difficulty_level_name":"مبتدئ","difficulty_level":2,"answers_data":[{"answer1":"الأبناء","is_correct":"false"},{"answer2":"الأخوة","is_correct":"false"},{"answer3":"الزوجين","is_correct":"true"},{"answer4":"الأقارب","is_correct":"false"}]},{"title":"هدف المنافقين من حديث الإفك العداوة لــ :","explain_answer":"لارتباط حادثة الإفك بالنبي صلى الله عليه وسلم ، ولم يكن هناك عداوة بين المنافقين والمشركين، أو الناس كلهم، أو العرب عامة.","year":2023,"score":2,"article":null,"difficulty_level_name":"مبتدئ","difficulty_level":2,"answers_data":[{"answer1":"الناس","is_correct":"false"},{"answer2":"الرسول صلى الله عليه وسلم","is_correct":"true"},{"answer3":"العرب","is_correct":"false"},{"answer4":"المشركين","is_correct":"false"}]},{"title":"<p>لكل دعوى دليل ودليل الإيمان .... أمام الاختبارات الصعبة.</p>\r\n","explain_answer":"","year":2023,"score":2,"article":null,"difficulty_level_name":"مبتدئ","difficulty_level":2,"answers_data":[{"answer1":"<p>الإعراض</p>\r\n","is_correct":"false"},{"answer2":"<p>التمرد</p>\r\n","is_correct":"false"},{"answer3":"<p>الثبات</p>\r\n","is_correct":"true"},{"answer4":"<p>التهاون</p>\r\n","is_correct":"false"}]},{"title":"<p>من وقع في الإشاعات وأقيم عليه الحد وتاب يكون الحد له ...</p>\r\n","explain_answer":"","year":2022,"score":2,"article":null,"difficulty_level_name":"مبتدئ","difficulty_level":2,"answers_data":[{"answer1":"<p>تطهيراً</p>\r\n","is_correct":"true"},{"answer2":"<p>تعذيباً</p>\r\n","is_correct":"false"},{"answer3":"<p>تشويهاً</p>\r\n","is_correct":"false"},{"answer4":"<p>تصحيحاً</p>\r\n","is_correct":"false"}]},{"title":"قال تعالى: (لُعِنُوا فِي الدُّنْيَا و َالآْخِرَة ِ) أول الآية قوله تعالى:","explain_answer":null,"year":2023,"score":2,"article":null,"difficulty_level_name":"مبتدئ","difficulty_level":2,"answers_data":[{"answer1":"وَلاَ يَأْتَل ِ أُولُو الفَضْل","is_correct":"false"},{"answer2":"إنَّ الذِين َيَرْمُون","is_correct":"true"},{"answer3":"يَوْمَئِذ ٍ يُوَفِّيهِم ُ اللهُ دِينَهُم","is_correct":"false"},{"answer4":"يَوْم َ تَشْهَد ُ عَلَيْهِم","is_correct":"false"}]},{"title":"قال تعالى: ( .... تُحِبُّونَ أَنْ يَغْفِرَ اللهُ  لَكُمْ)","explain_answer":null,"year":2023,"score":2,"article":null,"difficulty_level_name":"مبتدئ","difficulty_level":2,"answers_data":[{"answer1":"بل","is_correct":"false"},{"answer2":"كُنْتُمْ","is_correct":"false"},{"answer3":"مَأ","is_correct":"false"},{"answer4":"أَلَا","is_correct":"true"}]},{"title":"يجازي الله تعالى: الناس يوم القيامة بالجزاء العادل، الآية الدالة على ذلك :","explain_answer":null,"year":2023,"score":2,"article":null,"difficulty_level_name":"مبتدئ","difficulty_level":2,"answers_data":[{"answer1":"وَتَحْسَبُونَهُ هَيِّناً وَهُوَ عِندَ اللَّهِ عَظِيمٌ ","is_correct":"false"},{"answer2":"وَلْيَعْفُوا وَلْيَصْفَحُوا أَلَا تُحِبُّونَ ","is_correct":"false"},{"answer3":"يَوْمَئِذٍ يُوَفِّيهِمُ اللَّهُ دِينَهُمُ الْحَقَّ ","is_correct":"true"},{"answer4":"فَكَاتِبُوهُمْ إِنْ عَلِمْتُمْ فِيهِمْ خَيْراً","is_correct":"false"}]},{"title":"<p>يتوقف نجاح الأسرة على مدى الانسجام بين الزوجين الآية التي ورد فيها هذا المعنى :</p>\r\n","explain_answer":"","year":2023,"score":2,"article":null,"difficulty_level_name":"مبتدئ","difficulty_level":2,"answers_data":[{"answer1":"<p>واللهُ غَفُورٌ رَحِيمٌ</p>\r\n","is_correct":"false"},{"answer2":"<p>وَلْيَعْفُوا وَلْيَصْفَحُوا</p>\r\n","is_correct":"false"},{"answer3":"<p>وَلَوْلاَ فَضْلُ اللهِ عَلَيْكُمْ</p>\r\n","is_correct":"false"},{"answer4":"<p>الْخَبِيثَاتُ لِلْخَبِيثِينَ</p>\r\n","is_correct":"true"}]},{"title":"<p>يقصد بــ ( الفضل ) في قوله تعالى : ( أُولُو الْفَضْلِ مِنْكُمْ ) ...</p>\r\n","explain_answer":"<p>من معاني المفردات: أولو الفضل : أصحاب الفضل في <u>الدين</u>، وتستبعد بقية الخيارات.</p>\r\n","year":2021,"score":2,"article":null,"difficulty_level_name":"متوسط","difficulty_level":3,"answers_data":[{"answer1":"<p>الجاه</p>\r\n","is_correct":"false"},{"answer2":"<p>القرابة</p>\r\n","is_correct":"false"},{"answer3":"<p>الدين</p>\r\n","is_correct":"true"},{"answer4":"<p>المال</p>\r\n","is_correct":"false"}]},{"title":"<p>قال تعالى: (وَلَكِنَّ الَلَّهَ يُزَكِّي مَن ْ يَشَاء ُ واللهُ سَمِيع ٌ عَلِيم ٌ) تبدأ الآية التي بعدها بقوله تعالى:</p>\r\n","explain_answer":"<p><strong>۞</strong> يَا أَيُّهَا الَّذِينَ آمَنُوا لَا تَتَّبِعُوا خُطُوَاتِ الشَّيْطَانِ ۚ وَمَن يَتَّبِعْ خُطُوَاتِ الشَّيْطَانِ فَإِنَّهُ يَأْمُرُ بِالْفَحْشَاءِ وَالْمُنكَرِ ۚ وَلَوْلَا فَضْلُ اللَّهِ عَلَيْكُمْ وَرَحْمَتُهُ مَا زَكَىٰ مِنكُم مِّنْ أَحَدٍ أَبَدًا<strong> وَلَٰكِنَّ اللَّهَ يُزَكِّي مَن يَشَاءُ ۗ وَاللَّهُ سَمِيعٌ عَلِيمٌ (21)&nbsp;وَلَا يَأْتَلِ أُولُو الْفَضْلِ مِنكُمْ</strong> وَالسَّعَةِ أَن يُؤْتُوا أُولِي الْقُرْبَىٰ وَالْمَسَاكِينَ وَالْمُهَاجِرِينَ فِي سَبِيلِ اللَّهِ ۖ وَلْيَعْفُوا وَلْيَصْفَحُوا ۗ أَلَا تُحِبُّونَ أَن يَغْفِرَ اللَّهُ لَكُمْ ۗ وَاللَّهُ غَفُورٌ رَّحِيمٌ&nbsp;(22)</p>\r\n","year":2023,"score":2,"article":null,"difficulty_level_name":"متوسط","difficulty_level":3,"answers_data":[{"answer1":"<p>وَلاَ يَأْتَل ِ أُولُو الْفَضْل</p>\r\n","is_correct":"true"},{"answer2":"<p>إِنّ الَّلذِين َ يَرْمُون َ الْمُحْصَنَات</p>\r\n","is_correct":"false"},{"answer3":"<p>يَا أَيُّهَا اَّلذِين َ آَمَنُوا لاَ تَتَّبِعُوا</p>\r\n","is_correct":"false"},{"answer4":"<p>يَوْم َ تَشْهَد ُ عَلَيْهِم ْ أَلْسِنَتُهُم</p>\r\n","is_correct":"false"}]},{"title":"<p>ورد التراجع عن اليمين المعقودة في قوله تعالى : ( إِنَّ الَّذِينَ يَرْمُونَ الْمُحْصنَاتِ الْغَاَفِلَاتِ.... ).</p>\r\n","explain_answer":"<p><strong>اليمين المعقودة</strong> في سورة النور هي في <strong>اللعان بين الزوجين&nbsp;</strong><br />\r\nالتراجع يكون قبل الشهادة (<strong>اليمين</strong>) الخامسة</p>\r\n\r\n<p>&nbsp;<strong>وَيَدْرَأُ عَنْهَا الْعَذَابَ أَن تَشْهَدَ أَرْبَعَ شَهَادَاتٍ بِاللَّهِ ۙ إِنَّهُ لَمِنَ الْكَاذِبِينَ</strong></p>\r\n","year":2022,"score":1,"article":null,"difficulty_level_name":"مبتدئ","difficulty_level":2,"answers_data":[{"answer1":"<p>صح</p>\r\n","is_correct":"false"},{"answer2":"<p>خطأ</p>\r\n","is_correct":"true"}]},{"title":"على الإنسان الحذر من ألد أعدائه وهو :","explain_answer":"","year":2023,"score":2,"article":null,"difficulty_level_name":"مبتدئ","difficulty_level":2,"answers_data":[{"answer1":"رفيق السوء","is_correct":"false"},{"answer2":"الشيطان","is_correct":"true"},{"answer3":"اتباع الهوى","is_correct":"false"},{"answer4":"النفس","is_correct":"false"}]},{"title":"سبب تورط المسلمين في الإشاعة هو :","explain_answer":null,"year":2023,"score":2,"article":null,"difficulty_level_name":"مبتدئ","difficulty_level":2,"answers_data":[{"answer1":"إيمانهم بصحتها","is_correct":"false"},{"answer2":"النيل من رسول الله","is_correct":"false"},{"answer3":"وساوس الشيطان","is_correct":"true"},{"answer4":"إثارة الفتنة","is_correct":"false"}]},{"title":"<p>تفضل الله علينا بنعمة التوبة أولاً ونعمة الهداية ثانياً.</p>\r\n","explain_answer":"<p>تفضَّل الله علينا بنعمة <u>الهداية</u> أولاً، ونعمة <u>التوبة</u> ثانياً.</p>\r\n","year":2023,"score":1,"article":null,"difficulty_level_name":"متوسط","difficulty_level":3,"answers_data":[{"answer1":"<p>صح</p>\r\n","is_correct":"false"},{"answer2":"<p>خطأ</p>\r\n","is_correct":"true"}]},{"title":"<p>عالج القرآن الشرخ الاجتماعي للإشاعات من خلال ...</p>\r\n","explain_answer":"","year":2022,"score":2,"article":null,"difficulty_level_name":"مبتدئ","difficulty_level":2,"answers_data":[{"answer1":"<p>التخمين والتوقع</p>\r\n","is_correct":"false"},{"answer2":"<p>زيادة الإيمان</p>\r\n","is_correct":"false"},{"answer3":"<p>اتباع خطوات الشيطان</p>\r\n","is_correct":"false"},{"answer4":"<p>العفو والصفح</p>\r\n","is_correct":"true"}]},{"title":"<p>فعل الأخطاء الأخلاقية القبيحة من خطوات الشيطان .</p>\r\n","explain_answer":"","year":2021,"score":1,"article":null,"difficulty_level_name":"مبتدئ","difficulty_level":2,"answers_data":[{"answer1":"<p>صح</p>\r\n","is_correct":"true"},{"answer2":"<p>خطأ</p>\r\n","is_correct":"false"}]},{"title":"<p>على المؤمن أن يكون شديد الحذر فيما يقول أو يُردد لأن كلامه قد يعطي مشروعية لــ :</p>\r\n","explain_answer":"","year":2023,"score":2,"article":null,"difficulty_level_name":"مبتدئ","difficulty_level":2,"answers_data":[{"answer1":"<p>الباطل</p>\r\n","is_correct":"true"},{"answer2":"<p>الحق</p>\r\n","is_correct":"false"},{"answer3":"<p>الخير</p>\r\n","is_correct":"false"},{"answer4":"<p>الصلاح</p>\r\n","is_correct":"false"}]},{"title":"<p>لا يستوي في العقوبة المخطئ والمتعمد عند الله.</p>\r\n","explain_answer":"","year":2023,"score":1,"article":null,"difficulty_level_name":"مبتدئ","difficulty_level":2,"answers_data":[{"answer1":"<p>صح</p>\r\n","is_correct":"true"},{"answer2":"<p>خطأ</p>\r\n","is_correct":"false"}]},{"title":"إذا لم يستطع الشيطان جر  الإنسان نحو الكفر فإنه يوقعه في :","explain_answer":null,"year":2023,"score":2,"article":null,"difficulty_level_name":"مبتدئ","difficulty_level":2,"answers_data":[{"answer1":"الطاعة ","is_correct":"false"},{"answer2":"المعروف","is_correct":"false"},{"answer3":"الإثم","is_correct":"true"},{"answer4":"الوحل","is_correct":"false"}]},{"title":"<p>أعمال المنافق هي من تشهد عليه يوم القيامة.</p>\r\n","explain_answer":"<p><u>جوارح</u> المنافق هي من تشهد عليه يوم القيامة، قال تعالى: (يَوْمَ تَشْهَدُ عَلَيْهِمْ <u>أَلْسِنَتُهُمْ وَأَيْدِيهِمْ وَأَرْجُلُهُمْ..)</u></p>\r\n","year":2023,"score":1,"article":null,"difficulty_level_name":"متقدم","difficulty_level":4,"answers_data":[{"answer1":"<p>صح</p>\r\n","is_correct":"false"},{"answer2":"<p>خطأ</p>\r\n","is_correct":"true"}]},{"title":"أحد هذه الخيارات يتوقف عليه نجاح الحياة الزوجية :","explain_answer":"","year":2023,"score":2,"article":null,"difficulty_level_name":"مبتدئ","difficulty_level":2,"answers_data":[{"answer1":"التوافق والانسجام","is_correct":"true"},{"answer2":"البذل والعطاء","is_correct":"false"},{"answer3":"القوة والسيطرة","is_correct":"false"},{"answer4":"الغيرة الشديدة","is_correct":"false"}]},{"title":"<p>أقسم أبوبكر الصديق أن يقطع النفقة عن :</p>\r\n","explain_answer":"<p>حسبب حادثة الإفك: حيث كان مسطح بن أثاثة رضي الله عنه من بين الذين شاركوا في حادثة الإفك، وهي تلك الواقعة التي اتُهمت فيها السيدة عائشة رضي الله عنها بالزنا زورًا</p>\r\n","year":2023,"score":2,"article":null,"difficulty_level_name":"متوسط","difficulty_level":3,"answers_data":[{"answer1":"<p>صفوان بن المعطل</p>\r\n","is_correct":"false"},{"answer2":"<p>حذيفة بن اليمان</p>\r\n","is_correct":"false"},{"answer3":"<p>حمنة بنت جحش</p>\r\n","is_correct":"false"},{"answer4":"<p>مسطح بن أثاثة</p>\r\n","is_correct":"true"}]},{"title":"<p>أول الجوارح شهادة على الناس يوم القيامة بحسب ترتيب الآية في سورة النور :</p>\r\n","explain_answer":"","year":2023,"score":2,"article":null,"difficulty_level_name":"متوسط","difficulty_level":3,"answers_data":[{"answer1":"<p>الجلود</p>\r\n","is_correct":"false"},{"answer2":"<p>الألسن</p>\r\n","is_correct":"true"},{"answer3":"<p>الأيدي</p>\r\n","is_correct":"false"},{"answer4":"<p>الأرجل</p>\r\n","is_correct":"false"}]},{"title":"<p>أفلت المنافقون من العقوبة في الدنيا بسبب حذرهم الشديد.</p>\r\n","explain_answer":"","year":2023,"score":1,"article":null,"difficulty_level_name":"متوسط","difficulty_level":3,"answers_data":[{"answer1":"<p>صح</p>\r\n","is_correct":"true"},{"answer2":"<p>خطأ</p>\r\n","is_correct":"false"}]},{"title":"<p>( الفحشاء ) يقصد بها الأخطاء القبيحة من الأخلاق.</p>\r\n","explain_answer":"","year":2022,"score":1,"article":null,"difficulty_level_name":"مبتدئ","difficulty_level":2,"answers_data":[{"answer1":"<p>صح</p>\r\n","is_correct":"true"},{"answer2":"<p>خطأ</p>\r\n","is_correct":"false"}]},{"title":"<p>الإفلات من العقوبة الدنيوية إفلات من العقوبة الآخروية.</p>\r\n","explain_answer":"<p>أخبرنا الله عزوجل بأن الإفلات من العقوبة الدنيوية لا يعني الإفلات من العقوبة يوم القيامة التي هي أشد بأساً و أعظم خطراً مؤكداً أنه يوم القيامة لا ينفعهم تخفيهم ومكرهم؛ لأن جوارحهم ستكون شاهدة عليهم.</p>\r\n","year":2023,"score":1,"article":null,"difficulty_level_name":"مبتدئ","difficulty_level":2,"answers_data":[{"answer1":"<p>صح</p>\r\n","is_correct":"false"},{"answer2":"<p>خطأ</p>\r\n","is_correct":"true"}]},{"title":"العفو والصفح بين المؤمنين من الدروس المستفادة من آيات الدرس الرابع.","explain_answer":null,"year":2023,"score":1,"article":null,"difficulty_level_name":"مبتدئ","difficulty_level":2,"answers_data":[{"answer1":"صح","is_correct":"true"},{"answer2":"خطأ","is_correct":"false"}]},{"title":"<p>المحصنات هن اللاتي لا تخطر الفاحشة ببالهن.</p>\r\n","explain_answer":"<p><u>المحصنات</u> هن : النساء العفيفات. <u>الغافلات</u>: اللاتي لا تخطر الفاحشة ببالهن.</p>\r\n","year":2023,"score":1,"article":null,"difficulty_level_name":"متقدم","difficulty_level":4,"answers_data":[{"answer1":"<p>صح</p>\r\n","is_correct":"false"},{"answer2":"<p>خطأ</p>\r\n","is_correct":"true"}]},{"title":"<p>الأفعال والأقوال الطيبة تتناسب مع عباد الله الطيبين والطيبات.</p>\r\n","explain_answer":"<p>الأقوال والأفعال السيئة لا تتناسب مع الأشخاص الطيبين أو الصادقين، بل تتناسب مع <u>الخبيثين</u> ، ونستبعد المذنبين لأن المذنب إن تاب لم يكن من الخبيثين.</p>\r\n","year":2022,"score":1,"article":null,"difficulty_level_name":"مبتدئ","difficulty_level":2,"answers_data":[{"answer1":"<p>صح</p>\r\n","is_correct":"true"},{"answer2":"<p>خطأ</p>\r\n","is_correct":"false"}]},{"title":"<p>تأتي ضمن خطوات الشيطان عدا :</p>\r\n","explain_answer":"","year":2023,"score":2,"article":null,"difficulty_level_name":"مبتدئ","difficulty_level":2,"answers_data":[{"answer1":"<p>الوساوس</p>\r\n","is_correct":"false"},{"answer2":"<p>الإغواء والإغراء</p>\r\n","is_correct":"false"},{"answer3":"<p>المعروف</p>\r\n","is_correct":"true"},{"answer4":"<p>المنكر</p>\r\n","is_correct":"false"}]},{"title":"<p>إسقاط العقوبة عن المذنبين من عدل الله تعالى.</p>\r\n","explain_answer":"","year":2023,"score":1,"article":null,"difficulty_level_name":"مبتدئ","difficulty_level":2,"answers_data":[{"answer1":"<p>صح</p>\r\n","is_correct":"false"},{"answer2":"<p>خطأ</p>\r\n","is_correct":"true"}]},{"title":"<p>اتباع خطوات الشيطان يؤدي الى :</p>\r\n","explain_answer":"","year":2023,"score":2,"article":null,"difficulty_level_name":"مبتدئ","difficulty_level":2,"answers_data":[{"answer1":"<p>العدل</p>\r\n","is_correct":"false"},{"answer2":"<p>الإحسان</p>\r\n","is_correct":"false"},{"answer3":"<p>الفحشاء</p>\r\n","is_correct":"true"},{"answer4":"<p>حسن الخلق</p>\r\n","is_correct":"false"}]},{"title":"قال الله تعالى: (وَلَكِنَّ اللَّهَ يُزَكِّي مَنْ يَشَاءُ وَاللَّهُ .... ).","explain_answer":"","year":2023,"score":2,"article":null,"difficulty_level_name":"متوسط","difficulty_level":3,"answers_data":[{"answer1":"ذُو الْفَضْلِ الْعَظِيمِ","is_correct":"false"},{"answer2":"غَفُورٌ رَحِيمٌ","is_correct":"false"},{"answer3":"سَمِيعٌ عَلِيمٌ","is_correct":"true"},{"answer4":"غَفُورٌ حَلِيمٌ","is_correct":"false"}]},{"title":"<p>قال الله تعالى: (مَا زَكَى مِنْكُمْ مِنْ أَحَدٍ)&nbsp; &nbsp;أي ما أنفق منكم أحد من ماله .</p>\r\n","explain_answer":"","year":2022,"score":1,"article":null,"difficulty_level_name":"متوسط","difficulty_level":3,"answers_data":[{"answer1":"<p>صح</p>\r\n","is_correct":"false"},{"answer2":"<p>خطأ</p>\r\n","is_correct":"true"}]},{"title":"<p>قال الله تعالى : ( يَوْمَئِذٍ يُوَفِّيهِمُ اللَّهُ دِينَهُمُ الْحَقَّ ) المقصود بدينهم ...</p>\r\n","explain_answer":"<p>قال تعالى (يومئذ يوفيهم الله دينهم الحق ويعلمون أن الله هو الحق المبين)</p>\r\n\r\n<p>أي في هذا اليوم يوفيهم الله<strong> حسابهم و جزاءهم كاملا</strong> على أعمالهم بالعدل، ويعلمون في ذلك الموقف العظيم أن الله هو الحق المبين الذي هو حق، ووعده حق، ووعيده حق، وكل شيء منه حق، الذي لا يظلم أحدًا مثقال ذرة.</p>\r\n","year":2021,"score":2,"article":null,"difficulty_level_name":"متوسط","difficulty_level":3,"answers_data":[{"answer1":"<p>أعمالهم</p>\r\n","is_correct":"false"},{"answer2":"<p>شهادتهم</p>\r\n","is_correct":"false"},{"answer3":"<p>جزاءهم</p>\r\n","is_correct":"true"},{"answer4":"<p>اسلامهم</p>\r\n","is_correct":"false"}]},{"title":"<p>قال الله تعالى: (وَالْمُهَاجِرِينَ فِي سَبِيلِ اللَّهِ ................. أَلَا تُحِبُّونَ أَنْ يَغْفِرَ اللَّهُ لَكُمْ وَاللَّهُ غَفُورٌ رَّحِيمٌ)</p>\r\n","explain_answer":"","year":2021,"score":2,"article":null,"difficulty_level_name":"متوسط","difficulty_level":3,"answers_data":[{"answer1":"<p>وَابْنِ السَّبِيلِ</p>\r\n","is_correct":"false"},{"answer2":"<p>بِأَمْوَالِهِمْ وَأَنْفُسِهِمْ</p>\r\n","is_correct":"false"},{"answer3":"<p>وَلْيَعْفُوا وَلْيَصْفَحُوا</p>\r\n","is_correct":"true"},{"answer4":"<p>أُوْلَـئِكَ يَرْجُونَ رَحْمَه اللَّهِ</p>\r\n","is_correct":"false"}]},{"title":"<p>قال تعالى (أُولَئِك َ مُبَرَّءُون َ مِمَّا يَقُولُونَ) المقصود بـ (أُولَئِكَ) :</p>\r\n","explain_answer":"","year":2023,"score":2,"article":null,"difficulty_level_name":"متوسط","difficulty_level":3,"answers_data":[{"answer1":"<p>المتناقلون للإفك</p>\r\n","is_correct":"false"},{"answer2":"<p>المتهمون بالإفك</p>\r\n","is_correct":"true"},{"answer3":"<p>المبرؤون بالشهود</p>\r\n","is_correct":"false"},{"answer4":"<p>المتحدثون بالإفك دون قصد</p>\r\n","is_correct":"false"}]},{"title":"<p>قال الله تعالى : (وَلَا يَأْتَلِ أُوْلُوا الْفَضْلِ ... ) ختمت هذه الآية بقوله تعالى : ...........</p>\r\n","explain_answer":"","year":2021,"score":2,"article":null,"difficulty_level_name":"متوسط","difficulty_level":3,"answers_data":[{"answer1":"<p>اللَّهَ هُوَ الْغَفُورُ الرَّحِيمُ</p>\r\n","is_correct":"false"},{"answer2":"<p>إِنَّ اللَّهَ غَفُورٌ رَّحِيمٌ</p>\r\n","is_correct":"false"},{"answer3":"<p>وَهُوَ الْغَفُورُ الرَّحِيمُ</p>\r\n","is_correct":"false"},{"answer4":"<p>وَاللَّهُ غَفُورٌ رَّحِيمٌ</p>\r\n","is_correct":"true"}]},{"title":"<p>قال الله تعالى : ( يَرْمُونَ الْمُحْصَنَاتِ ) معنى ( يَرْمُونَ ) أي ...</p>\r\n","explain_answer":"","year":2022,"score":2,"article":null,"difficulty_level_name":"مبتدئ","difficulty_level":2,"answers_data":[{"answer1":"<p>يمنعون</p>\r\n","is_correct":"false"},{"answer2":"<p>يقيمون</p>\r\n","is_correct":"false"},{"answer3":"<p>يدَّعون</p>\r\n","is_correct":"false"},{"answer4":"<p>يقذفون</p>\r\n","is_correct":"true"}]},{"title":"<p>قال الله تعالى : ( أَنْ يُؤْتُوا أُولِي الْقُرْبَى وَالْمَسَاكِينَ .................. ).ِ</p>\r\n","explain_answer":"<p>قال تعالى:﴿ وَلَا يَأْتَلِ أُولُو الْفَضْلِ مِنكُمْ وَالسَّعَةِ أَن يُؤْتُوا أُولِي الْقُرْبَىٰ وَالْمَسَاكِينَ <strong>وَالْمُهَاجِرِينَ فِي سَبِيلِ اللَّهِ ۖ</strong> وَلْيَعْفُوا وَلْيَصْفَحُوا ۗ أَلَا تُحِبُّونَ أَن يَغْفِرَ اللَّهُ لَكُمْ ۗ وَاللَّهُ غَفُورٌ رَّحِيمٌ﴾<br />\r\n<strong>[&nbsp;النور: 22]</strong></p>\r\n","year":2022,"score":2,"article":null,"difficulty_level_name":"متوسط","difficulty_level":3,"answers_data":[{"answer1":"<p>وَابْنَ السَّبِيل</p>\r\n","is_correct":"false"},{"answer2":"<p>وَالْعَامِلِينَ عَلَيْهَا</p>\r\n","is_correct":"false"},{"answer3":"<p>وَالْمُهَاجِرِينَ فِي سَبِيلِ اللَّهِ</p>\r\n","is_correct":"true"},{"answer4":"<p>وَالْجَارِ ذِي الْقُرْبَى</p>\r\n","is_correct":"false"}]},{"title":"<p>قال الله تعالى : ( ............................ الْغَافِلَاتِ الْمُؤْمِنَاتِ لُعِنُوا فِي الدُّنْيَا و َالْآَخِرَةِ ).</p>\r\n","explain_answer":"","year":2022,"score":2,"article":null,"difficulty_level_name":"متوسط","difficulty_level":3,"answers_data":[{"answer1":"<p>وَالّذِينَ يَرْمُونَ أَزْوَاجَهُمْ</p>\r\n","is_correct":"false"},{"answer2":"<p>وَالّذِينَ يَرْمُونَ الْمُحْصَنَاتِ</p>\r\n","is_correct":"false"},{"answer3":"<p>إِنَّ الّذِينَ يَرْمُونَ الْمُحْصَنَاتِ</p>\r\n","is_correct":"true"},{"answer4":"<p>إِنَّ الّذِينَ يُحِبُّونَ</p>\r\n","is_correct":"false"}]},{"title":"<p>قال الله تعالى : ( إِلاّ ......... تَابُوا مِنْ بَعْدِ ذَلِكَ وَأَصْلَحُوا فَإِنَّ اللَّهَ غَفُورٌ رَّحِيمٌ )</p>\r\n","explain_answer":"","year":2021,"score":2,"article":null,"difficulty_level_name":"مبتدئ","difficulty_level":2,"answers_data":[{"answer1":"<p>رِجَالاً</p>\r\n","is_correct":"false"},{"answer2":"<p>لِمَنْ</p>\r\n","is_correct":"false"},{"answer3":"<p>الَّذِينَ</p>\r\n","is_correct":"true"},{"answer4":"<p>قَلِيلاً</p>\r\n","is_correct":"false"}]},{"title":"<p>قال الله تعالى : ( وَلَا يَأْتَلِ أُولُو الْفَضْلِ مِنْكُمْ وَالسَّعَةِ ) معنى ( يَأْتَلِ ) لا...</p>\r\n","explain_answer":"","year":2021,"score":2,"article":null,"difficulty_level_name":"مبتدئ","difficulty_level":2,"answers_data":[{"answer1":"<p>ينفق</p>\r\n","is_correct":"false"},{"answer2":"<p>يقسم</p>\r\n","is_correct":"true"},{"answer3":"<p>يحمل</p>\r\n","is_correct":"false"},{"answer4":"<p>يغضب</p>\r\n","is_correct":"false"}]},{"title":"<p>قال الله تعالى : ( وَمَن ْ يَتَّبِع ْ خُطُوَاتِ الشَّيطَانِ فَإِنَهُ يَأْمُرُ بِالْفَحْشَاءِ وَالْمُنْكَرِ وَلَوْلاَ فَضْلُ اللهِ ..................... ).</p>\r\n","explain_answer":"","year":2022,"score":2,"article":null,"difficulty_level_name":"مبتدئ","difficulty_level":2,"answers_data":[{"answer1":"<p>عَلَيْكَ</p>\r\n","is_correct":"false"},{"answer2":"<p>يُؤْتِيهِ</p>\r\n","is_correct":"false"},{"answer3":"<p>عَلَيْكُمْ</p>\r\n","is_correct":"true"},{"answer4":"<p>وَرَحْمَتَهُ</p>\r\n","is_correct":"false"}]},{"title":"<p>قال الله تعالى : ( لُعِنُوا فِي الدُّنْيَا و َالْآَخِرَةِ وَلَهُمْ عَذَابٌ .................. ).</p>\r\n","explain_answer":"","year":2022,"score":2,"article":null,"difficulty_level_name":"مبتدئ","difficulty_level":2,"answers_data":[{"answer1":"<p>أَلِيمٌ</p>\r\n","is_correct":"false"},{"answer2":"<p>عَظِيمٌ</p>\r\n","is_correct":"true"},{"answer3":"<p>مُهِينٌ</p>\r\n","is_correct":"false"},{"answer4":"<p>مُقِيمٌ</p>\r\n","is_correct":"false"}]},{"title":"<p>قال الله تعالى : ( وَالْمُهَاجِرِينَ فِي سَبِيلِ اللَّهِ ...................... أَلَا تُحِبُّونَ أَن يَغْفِرَ اللَّهُ لَكُمْ ).</p>\r\n","explain_answer":"","year":2022,"score":2,"article":null,"difficulty_level_name":"مبتدئ","difficulty_level":2,"answers_data":[{"answer1":"<p>وَابْنِ السَّبِيلِ</p>\r\n","is_correct":"false"},{"answer2":"<p>بِأَمْوَالِهِمْ وَأَنْفُسِهِمْ</p>\r\n","is_correct":"false"},{"answer3":"<p>وَلْيَعْفُوا وَلْيَصْفَحُوا</p>\r\n","is_correct":"true"},{"answer4":"<p>أُولَئِكَ يَرْجُونَ رَحْمَةَ اللَّهِ</p>\r\n","is_correct":"false"}]},{"title":"<p>قال تعالى: (وَلَا يَأۡتَلِ أُوْلُواْ&nbsp; ...) آخر الآية قوله تعالى:</p>\r\n","explain_answer":"","year":2023,"score":2,"article":null,"difficulty_level_name":"متوسط","difficulty_level":3,"answers_data":[{"answer1":"<p>واللهَ غَفُورٌحَلِيم</p>\r\n","is_correct":"false"},{"answer2":"<p>وَٱللَّهُ سَمِيعٌ عَلِيمٞ</p>\r\n","is_correct":"false"},{"answer3":"<p>واللهُ عَزِيز ٌ حَكِيم</p>\r\n","is_correct":"false"},{"answer4":"<p>وَٱللَّهُ غَفُورٞ رَّحِيمٌ</p>\r\n","is_correct":"true"}]},{"title":"<p>قال تعالى: (لُعِنُوا فِي الدُّنْيَا وَالْآَخِرَةِ وَلَهُمْ عَذَابٌ عَظِيمٌ ) الآية التي قبلها بدأت بقوله تعالى :</p>\r\n","explain_answer":"","year":2023,"score":2,"article":null,"difficulty_level_name":"متوسط","difficulty_level":3,"answers_data":[{"answer1":"<p>يَوْمَ تَشْهَدُ عَلَيْهِمْ</p>\r\n","is_correct":"false"},{"answer2":"<p>يَوْمَئِذٍ يُوَفِّيهِمُ&nbsp;اللهُ</p>\r\n","is_correct":"false"},{"answer3":"<p>وَلاَ يَأْتَلِ أُولُو الْفَضْلِ</p>\r\n","is_correct":"true"},{"answer4":"<p>وَلَوْلَا فَضْلُ اللهِ عَلَيْكُمْ</p>\r\n","is_correct":"false"}]},{"title":"قال تعالى: (وَمَنْ يَتَّبِعْ خُطُوَاتِ  الشَّيْطَانِ فَإنَّهُ.... )","explain_answer":null,"year":2023,"score":2,"article":null,"difficulty_level_name":"مبتدئ","difficulty_level":2,"answers_data":[{"answer1":"لَكُمْ عَدُوٌّ مُّبِينٌ ","is_correct":"false"},{"answer2":"آثِمٌ قَلْبُهُ ","is_correct":"false"},{"answer3":"عَدُوٍّ لَّكُمْ ","is_correct":"false"},{"answer4":"يَأْمُرُ بِالْفَحْشَاء وَالْمُنكَرِ","is_correct":"true"}]},{"title":"ورد لفظ (الْمُهَاجِرِينَ) في قوله تعالى:","explain_answer":null,"year":2023,"score":2,"article":null,"difficulty_level_name":"مبتدئ","difficulty_level":2,"answers_data":[{"answer1":"لَيْسَ عَلَيْكُمْ جُنَاحٌ","is_correct":"false"},{"answer2":"وَلاَ يَأْتَلِ أُولُو الْفَضْلِ مِنْكُمْ","is_correct":"true"},{"answer3":"مَنْ يُطِعِ اللهَ","is_correct":"false"},{"answer4":"لاَ تَجْعَلُوا دُعَاءَ الرَّسُولِ","is_correct":"false"}]},{"title":"<p>قال تعالى: (يَوْمَئِذٍ يُوَفِّيهِمُ اللَّهُ دِينَهُمُ الْحَقَّ ) المقصود بالدين الحق الإسلام.</p>\r\n","explain_answer":"<p>قال تعالى (يومئذ يوفيهم الله دينهم الحق ويعلمون أن الله هو الحق المبين)</p>\r\n\r\n<p>أي في هذا اليوم يوفيهم الله<strong> حسابهم و جزاءهم كاملا</strong> على أعمالهم بالعدل، ويعلمون في ذلك الموقف العظيم أن الله هو الحق المبين الذي هو حق، ووعده حق، ووعيده حق، وكل شيء منه حق، الذي لا يظلم أحدًا مثقال ذرة.</p>\r\n","year":2023,"score":1,"article":null,"difficulty_level_name":"متوسط","difficulty_level":3,"answers_data":[{"answer1":"<p>صح</p>\r\n","is_correct":"false"},{"answer2":"<p>خطأ</p>\r\n","is_correct":"true"}]},{"title":"<p>قال تعالى: (وَالطَّيِبُون َ لِلطَّيِبَات ِ ....)</p>\r\n","explain_answer":"<p>قال تعالى: ﴿ ٱلۡخَبِيثَٰتُ لِلۡخَبِيثِينَ وَٱلۡخَبِيثُونَ لِلۡخَبِيثَٰتِۖ وَٱلطَّيِّبَٰتُ لِلطَّيِّبِينَ وَٱلطَّيِّبُونَ لِلطَّيِّبَٰتِۚ<strong> أُوْلَٰٓئِكَ مُبَرَّءُونَ</strong> مِمَّا يَقُولُونَۖ لَهُم مَّغۡفِرَةٞ وَرِزۡقٞ كَرِيمٞ&nbsp;﴾</p>\r\n","year":2023,"score":2,"article":null,"difficulty_level_name":"متوسط","difficulty_level":3,"answers_data":[{"answer1":"<p>وَأَن الله رَءُوف ٌ رَحِيم</p>\r\n","is_correct":"false"},{"answer2":"<p>وَالطَّيِبَات ُ لِلطَّيِبِين</p>\r\n","is_correct":"false"},{"answer3":"<p>أُولئَك َ مُبَرَّءُون</p>\r\n","is_correct":"true"},{"answer4":"<p>وَالْخَبِيثُون َ لِلْخَبِيثَات</p>\r\n","is_correct":"false"}]},{"title":"<p>ما يسبق قوله تعالى: (مَا زَكَى مِنْكُم ْ مِن ْ أَحَدٍ) :</p>\r\n","explain_answer":"","year":2023,"score":2,"article":null,"difficulty_level_name":"متوسط","difficulty_level":3,"answers_data":[{"answer1":"<p>وَرَحْمَتُه ُ فِي الدُّنْيَا و َالْأَخِرَةِ</p>\r\n","is_correct":"false"},{"answer2":"<p>وَلَوْلاَ فَضْلُ اللهِ عَلَيْكُمْ وَرَحْمَتُهُ</p>\r\n","is_correct":"true"},{"answer3":"<p>وَلاَ يَأْتَلِ أُولُو الْفَضْلِ</p>\r\n","is_correct":"false"},{"answer4":"<p>ظَنَّ الْمُؤْمِنُونَ وَالْمُؤْمِنَاتُ</p>\r\n","is_correct":"false"}]},{"title":"الجزاء من جنس العمل، الآية الدالة على ذلك قوله تعالى:","explain_answer":null,"year":2023,"score":2,"article":null,"difficulty_level_name":"متوسط","difficulty_level":3,"answers_data":[{"answer1":"وَلْيَعْفُوا وَلْيَصْفَحُوا","is_correct":"true"},{"answer2":"فَاجْلِدُوهُمْ ثَمَانِينَ جَلْدَةً","is_correct":"false"},{"answer3":"وَلَوْلَا فَضْلُ اللهِ","is_correct":"false"},{"answer4":"إِلَّا الَّذِينَ تَابُوا","is_correct":"false"}]},{"title":"<p>قال الله تعالى : ( الْخَبِيثَاتُ لِلْخَبِيثِينَ وَالْخَبِيثُونَ لِلْخَبِيثَاتِ ) تدل الآية على ...</p>\r\n","explain_answer":"","year":2022,"score":2,"article":null,"difficulty_level_name":"مبتدئ","difficulty_level":2,"answers_data":[{"answer1":"<p>تأثير الإشاعات</p>\r\n","is_correct":"false"},{"answer2":"<p>الانسجام والتوافق</p>\r\n","is_correct":"true"},{"answer3":"<p>الانحراف والسوء</p>\r\n","is_correct":"false"},{"answer4":"<p>تحريم الزنى</p>\r\n","is_correct":"false"}]},{"title":"<p>قال الله تعالى : ( إِنَّ الَّذِينَ يَرْمُونَ الْمُحْصَنَاتِ .......... ) ختمت هذه الآية بقوله تعالى ...</p>\r\n","explain_answer":"","year":2021,"score":2,"article":null,"difficulty_level_name":"مبتدئ","difficulty_level":2,"answers_data":[{"answer1":"<p>فَلَهُمْ عَذَابٌ مُهِينٌ</p>\r\n","is_correct":"false"},{"answer2":"<p>وَلَهُمْ عَذَابٌ عَظِيمٌ</p>\r\n","is_correct":"true"},{"answer3":"<p>لَهُمْ عَذَابٌ مُهِينٌ</p>\r\n","is_correct":"false"},{"answer4":"<p>لَهُ عَذَابٌ عَظِيمٌ</p>\r\n","is_correct":"false"}]},{"title":"<p>الآية التي فيها لفظ (لاَ تَتبِعُوا) بدأت بقوله تعالى:</p>\r\n","explain_answer":"","year":2023,"score":2,"article":null,"difficulty_level_name":"مبتدئ","difficulty_level":2,"answers_data":[{"answer1":"<p>والذِين َ آَمَنُوا</p>\r\n","is_correct":"false"},{"answer2":"<p>يَا أَيُّهَا الذِين َ آَمَنُوا</p>\r\n","is_correct":"true"},{"answer3":"<p>إِنَّ الذِين َ آَمَنُوا</p>\r\n","is_correct":"false"},{"answer4":"<p>إِنَّ الذِين َ يَرْمُونَ</p>\r\n","is_correct":"false"}]},{"title":"<p>تطهير النفوس البشرية مبني على علم الله تعالى، الآية الدالة على ذلك قوله تعالى: (وَلَكِنَّ اللهَ ....)</p>\r\n","explain_answer":"","year":2023,"score":2,"article":null,"difficulty_level_name":"مبتدئ","difficulty_level":2,"answers_data":[{"answer1":"<p>يُزَكِّي مَن ْ يَشَاءُ</p>\r\n","is_correct":"true"},{"answer2":"<p>يَفْعَل ُمَا يُرِيدُ</p>\r\n","is_correct":"false"},{"answer3":"<p>يُسَلِّط ُ رُسُلَهُ</p>\r\n","is_correct":"false"},{"answer4":"<p>يَجْتَبِي مِن ْ رُسُلِهِ</p>\r\n","is_correct":"false"}]},{"title":"<p>تفسير قوله تعالى : ( وَلا يَأْتَلِ ) قسم من ذوي الفضل في الدين والسعة في المال .</p>\r\n","explain_answer":"","year":2021,"score":1,"article":null,"difficulty_level_name":"مبتدئ","difficulty_level":2,"answers_data":[{"answer1":"<p>صح</p>\r\n","is_correct":"true"},{"answer2":"<p>خطأ</p>\r\n","is_correct":"false"}]},{"title":"<p>حذرنا الله تعالى من مكائد الشيطان وانتهى التحذير بقوله تعالى : ..............</p>\r\n","explain_answer":"","year":2022,"score":2,"article":null,"difficulty_level_name":"متوسط","difficulty_level":3,"answers_data":[{"answer1":"<p>سَمِيعٌ عَلِيمٌ</p>\r\n","is_correct":"true"},{"answer2":"<p>عَلِيمٌ حَكِيمٌ</p>\r\n","is_correct":"false"},{"answer3":"<p>غَفُورٌ رَحِيمٌ</p>\r\n","is_correct":"false"},{"answer4":"<p>رَءُوفٌ رَحِيمٌ</p>\r\n","is_correct":"false"}]},{"title":"<p>تمثل الخيارات التالية دروساً وقواعد إيمانية عدا :</p>\r\n","explain_answer":"","year":2023,"score":2,"article":null,"difficulty_level_name":"مبتدئ","difficulty_level":2,"answers_data":[{"answer1":"<p>التصدي للإشاعة</p>\r\n","is_correct":"false"},{"answer2":"<p>حسن الظن</p>\r\n","is_correct":"false"},{"answer3":"<p>الانقياد للشيطان</p>\r\n","is_correct":"true"},{"answer4":"<p>العفو والصفح</p>\r\n","is_correct":"false"}]},{"title":"تراجَع المسلمون عن أيمانهم استجابة لأمر الله تعالى.","explain_answer":"<p dir=\"rtl\" style=\"text-align: right;\">كان من تداعيات حادثة الافك أن بعض الصحابة أقسمو أن لا يتصدقو على اي شخص خاض في الإفك ولكن الاسلام أراد للمؤمنين أن يترفعو على الآلام ولا يستسلمو لردود الفعل السلبية فوجههم الى العفو والصفح ووعدهم بالعفو والمغفرة مقابل عفوهم ومغفرتهم لمن أساء وهنالك تراجَع المسلمون عن أيمانهم استجابة لأمر الله تعالى وطمعاً في عفوه&nbsp;ورضوانه .</p>\r\n","year":2023,"score":1,"article":null,"difficulty_level_name":"متوسط","difficulty_level":3,"answers_data":[{"answer1":"صح","is_correct":"true"},{"answer2":"خطأ","is_correct":"false"}]},{"title":"<p>تختلف العقوبة في الإشاعات الكاذبة باختلاف الإثم وأعلى مستوياته :</p>\r\n","explain_answer":"","year":2023,"score":2,"article":null,"difficulty_level_name":"متوسط","difficulty_level":3,"answers_data":[{"answer1":"<p>التوقع والتخمين</p>\r\n","is_correct":"false"},{"answer2":"<p>تعمد الافتراء</p>\r\n","is_correct":"true"},{"answer3":"<p>النقل دون تثبت</p>\r\n","is_correct":"false"},{"answer4":"<p>السماع دون إنكار</p>\r\n","is_correct":"false"}]},{"title":"<p>تفضل الله تعالى على الناس بنعمة الهداية أولاً ونعمة .... ثانياً .</p>\r\n","explain_answer":"","year":2023,"score":2,"article":null,"difficulty_level_name":"مبتدئ","difficulty_level":2,"answers_data":[{"answer1":"<p>الخير</p>\r\n","is_correct":"false"},{"answer2":"<p>اليقين</p>\r\n","is_correct":"false"},{"answer3":"<p>التوبة</p>\r\n","is_correct":"true"},{"answer4":"<p>الصدق</p>\r\n","is_correct":"false"}]},{"title":"<p>حكم من يتبع غوايات الشيطان ...</p>\r\n","explain_answer":"","year":2021,"score":2,"article":null,"difficulty_level_name":"مبتدئ","difficulty_level":2,"answers_data":[{"answer1":"<p>محرم</p>\r\n","is_correct":"true"},{"answer2":"<p>مكروه</p>\r\n","is_correct":"false"},{"answer3":"<p>مباح</p>\r\n","is_correct":"false"},{"answer4":"<p>مندوب</p>\r\n","is_correct":"false"}]},{"title":"<p>جعل الله الجزاء من جنس العمل.</p>\r\n","explain_answer":"","year":2022,"score":1,"article":null,"difficulty_level_name":"مبتدئ","difficulty_level":2,"answers_data":[{"answer1":"<p>صح</p>\r\n","is_correct":"true"},{"answer2":"<p>خطأ</p>\r\n","is_correct":"false"}]},{"title":"<p>حماية المجتمع من النتائج السلبية للأخطاء يتحقق بتربيته على ...</p>\r\n","explain_answer":"","year":2022,"score":2,"article":null,"difficulty_level_name":"مبتدئ","difficulty_level":2,"answers_data":[{"answer1":"<p>العفو</p>\r\n","is_correct":"true"},{"answer2":"<p>العزل</p>\r\n","is_correct":"false"},{"answer3":"<p>النفي</p>\r\n","is_correct":"false"},{"answer4":"<p>الإنذار</p>\r\n","is_correct":"false"}]},{"title":"قال تعالى: (فَإِنَّهُ يَأْمُرُ بِالْفَحْشَاءِ وَالْمُنْكَرِ) يعود الضمير في الآية على :","explain_answer":null,"year":2023,"score":2,"article":null,"difficulty_level_name":"مبتدئ","difficulty_level":2,"answers_data":[{"answer1":"المشرك","is_correct":"false"},{"answer2":"الشيطان","is_correct":"true"},{"answer3":"الكافر","is_correct":"false"},{"answer4":"المنافق","is_correct":"false"}]},{"title":"<p>قال تعالى : ( إِنَّ ٱلَّذِينَ يَرۡمُونَ ٱلۡمُحۡصَنَاتِ ....)</p>\r\n","explain_answer":"","year":2023,"score":2,"article":null,"difficulty_level_name":"مبتدئ","difficulty_level":2,"answers_data":[{"answer1":"<p>الْغَافِلاَت</p>\r\n","is_correct":"true"},{"answer2":"<p>مِن َ الْمُؤْمِنَات</p>\r\n","is_correct":"false"},{"answer3":"<p>مِن َالنِسَاء</p>\r\n","is_correct":"false"},{"answer4":"<p>مِن َ الَّذِين َ أُوتُوا اْلكِتَاب</p>\r\n","is_correct":"false"}]},{"title":"<p>قال تعالى: (فإنَه ُ يَأْمُر ُ بِالْفَحْشَاءِ) يقصد بالفحشاء كل التجاوزات المنكرة في شرع الله تعالى.</p>\r\n","explain_answer":"","year":2023,"score":1,"article":null,"difficulty_level_name":"متقدم","difficulty_level":4,"answers_data":[{"answer1":"<p>صح</p>\r\n","is_correct":"false"},{"answer2":"<p>خطأ</p>\r\n","is_correct":"true"}]},{"title":"<p>قال تعالى: (لاَ تَتَّبعُوا خُطُوَات ِ الشَّيْطَانِ) المقصود بخطوات :</p>\r\n","explain_answer":"","year":2023,"score":2,"article":null,"difficulty_level_name":"مبتدئ","difficulty_level":2,"answers_data":[{"answer1":"<p>مسارات</p>\r\n","is_correct":"false"},{"answer2":"<p>اتجاهات</p>\r\n","is_correct":"false"},{"answer3":"<p>وساوس</p>\r\n","is_correct":"true"},{"answer4":"<p>أساليب</p>\r\n","is_correct":"false"}]},{"title":"<p>قال تعالى: (أَن ْ يُؤْتُوا أُولِي الْقُرْبَى وَالْمَسَاكِين َ و .....)</p>\r\n","explain_answer":"","year":2023,"score":2,"article":null,"difficulty_level_name":"متوسط","difficulty_level":3,"answers_data":[{"answer1":"<p>ابْن َالسَّبِيل</p>\r\n","is_correct":"false"},{"answer2":"<p>الْعَامِلِين</p>\r\n","is_correct":"false"},{"answer3":"<p>الْجَارِ ذِي الْقُرْبَى</p>\r\n","is_correct":"false"},{"answer4":"<p>الْمُهَاجِرِين</p>\r\n","is_correct":"true"}]},{"title":"<p>قال تعالى: (....لُعِنُوا فِي الدُّنْيَا وَالْأَخِرَةِ) الآية بدأت بقوله تعالى:</p>\r\n","explain_answer":"","year":2023,"score":2,"article":null,"difficulty_level_name":"متوسط","difficulty_level":3,"answers_data":[{"answer1":"<p>وَالَّذِينَ يَرْمُونَ أَزْوَاجَهُمْ</p>\r\n","is_correct":"false"},{"answer2":"<p>إِنَّ الذِينَ يَرْمُونَ الْمُحْصَنَاتِ</p>\r\n","is_correct":"true"},{"answer3":"<p>إِنَّ الَّذِينَ يُحِبُّونَ أَنْ تَشِيعَ</p>\r\n","is_correct":"false"},{"answer4":"<p>وَالَّذِينَ يَرْمُونَ الْمُحْصَنَاتِ</p>\r\n","is_correct":"false"}]},{"title":"<p>قال تعالى: (إِنَّ الَّذِين َ يَرْمُون َ الْمُحْصَنَات ِ الْغَافِلَاتِ) أي الغافلات عن :</p>\r\n","explain_answer":"","year":2023,"score":2,"article":null,"difficulty_level_name":"متوسط","difficulty_level":3,"answers_data":[{"answer1":"<p>العفة</p>\r\n","is_correct":"false"},{"answer2":"<p>الغيبة</p>\r\n","is_correct":"false"},{"answer3":"<p>الحشمة</p>\r\n","is_correct":"false"},{"answer4":"<p>الفاحشة</p>\r\n","is_correct":"true"}]}],"scope":"lesson"}]