[{"total_degree":14,"questionsData":[{"title":"Sailors put the oars on the mast.","explain_answer":"","year":2023,"score":1,"article":null,"difficulty_level_name":"متوسط","difficulty_level":3,"answers_data":[{"answer1":"TRUE","is_correct":"false"},{"answer2":"FALSE","is_correct":"true"}]},{"title":"<p>Nets are used to get rid of fish.</p>\r\n","explain_answer":"<p>&nbsp;Nets are commonly used in fishing to <strong>catch </strong>fish, not to get rid of them.</p>\r\n","year":2023,"score":1,"article":null,"difficulty_level_name":"متوسط","difficulty_level":3,"answers_data":[{"answer1":"<p>TRUE</p>\r\n","is_correct":"false"},{"answer2":"<p>FALSE</p>\r\n","is_correct":"true"}]},{"title":"<p>Bow and stern are parts of the ship.</p>\r\n","explain_answer":"","year":2023,"score":1,"article":null,"difficulty_level_name":"مبتدئ","difficulty_level":2,"answers_data":[{"answer1":"<p>TRUE</p>\r\n","is_correct":"true"},{"answer2":"<p>FALSE</p>\r\n","is_correct":"false"}]},{"title":"<p>Masts are used to hold the sails in ships.</p>\r\n","explain_answer":"","year":2023,"score":1,"article":null,"difficulty_level_name":"متوسط","difficulty_level":3,"answers_data":[{"answer1":"<p>TRUE</p>\r\n","is_correct":"true"},{"answer2":"<p>FALSE</p>\r\n","is_correct":"false"}]},{"title":"<p>The cabin is a small house in which you live.</p>\r\n","explain_answer":"<p><strong>Cabin </strong>(ship) <strong>a&nbsp;small, enclosed room</strong> on a ship used for passengers or crew.<br />\r\nMay have beds, furniture, and storage space.<br />\r\n<strong>Not a permanent residence</strong>, but provides living quarters for a journey.</p>\r\n","year":2022,"score":1,"article":null,"difficulty_level_name":"مبتدئ","difficulty_level":2,"answers_data":[{"answer1":"<p>TRUE</p>\r\n","is_correct":"false"},{"answer2":"<p>FALSE</p>\r\n","is_correct":"true"}]},{"title":"<p>The front part of the ship is called a mast.</p>\r\n","explain_answer":"","year":2022,"score":1,"article":null,"difficulty_level_name":"مبتدئ","difficulty_level":2,"answers_data":[{"answer1":"<p>TRUE</p>\r\n","is_correct":"false"},{"answer2":"<p>FALSE</p>\r\n","is_correct":"true"}]},{"title":"<p>The deck is the top level of the ship.</p>\r\n","explain_answer":"","year":2022,"score":1,"article":null,"difficulty_level_name":"متوسط","difficulty_level":3,"answers_data":[{"answer1":"<p>TRUE</p>\r\n","is_correct":"true"},{"answer2":"<p>FALSE</p>\r\n","is_correct":"false"}]},{"title":"To row is to move the boat by using sail.","explain_answer":"","year":2023,"score":1,"article":null,"difficulty_level_name":"متوسط","difficulty_level":3,"answers_data":[{"answer1":"TRUE","is_correct":"false"},{"answer2":"FALSE","is_correct":"true"}]},{"title":"Table, sofa and armchair are pieces of furniture.","explain_answer":null,"year":2023,"score":1,"article":null,"difficulty_level_name":"مبتدئ","difficulty_level":2,"answers_data":[{"answer1":"TRUE","is_correct":"true"},{"answer2":"FALSE","is_correct":"false"}]},{"title":"\"Pulling up the sail\" means \"putting it down\".","explain_answer":null,"year":2023,"score":1,"article":null,"difficulty_level_name":"متوسط","difficulty_level":3,"answers_data":[{"answer1":"TRUE","is_correct":"false"},{"answer2":"FALSE","is_correct":"true"}]},{"title":"<p>The cabin is a small house in which you live.</p>\r\n","explain_answer":"<p><strong>Cabin </strong>(ship) <strong>a&nbsp;small, enclosed room</strong> on a ship used for passengers or crew.<br />\r\nMay have beds, furniture, and storage space.<br />\r\n<strong>Not a permanent residence</strong>, but provides living quarters for a journey.</p>\r\n","year":2022,"score":1,"article":null,"difficulty_level_name":"مبتدئ","difficulty_level":2,"answers_data":[{"answer1":"<p>TRUE</p>\r\n","is_correct":"false"},{"answer2":"<p>FALSE</p>\r\n","is_correct":"true"}]},{"title":"<p>The front part of the ship is called a mast.</p>\r\n","explain_answer":"","year":2022,"score":1,"article":null,"difficulty_level_name":"مبتدئ","difficulty_level":2,"answers_data":[{"answer1":"<p>TRUE</p>\r\n","is_correct":"false"},{"answer2":"<p>FALSE</p>\r\n","is_correct":"true"}]},{"title":"<p>A group of connected words is called word set.</p>\r\n","explain_answer":"","year":2022,"score":1,"article":null,"difficulty_level_name":"مبتدئ","difficulty_level":2,"answers_data":[{"answer1":"<p>TRUE</p>\r\n","is_correct":"true"},{"answer2":"<p>FALSE</p>\r\n","is_correct":"false"}]},{"title":"<p>Bow and stern are parts of furniture.</p>\r\n","explain_answer":"","year":2023,"score":1,"article":null,"difficulty_level_name":"مبتدئ","difficulty_level":2,"answers_data":[{"answer1":"<p>TRUE</p>\r\n","is_correct":"false"},{"answer2":"<p>FALSE</p>\r\n","is_correct":"true"}]}],"scope":"lesson"}]