[{"total_degree":39,"questionsData":[{"title":"تثبت جريمة فعل القتل بأنواعه الثلاثة بالإقرار أو شاهدين.","explain_answer":"","year":2023,"score":1,"article":null,"difficulty_level_name":"مبتدئ","difficulty_level":2,"answers_data":[{"answer1":"صح","is_correct":"true"},{"answer2":"خطأ","is_correct":"false"}]},{"title":"<p>حقن طبيب شخصا ً بإبرة عامداً قتله فمات يوجب ...</p>\r\n","explain_answer":"","year":2023,"score":2,"article":null,"difficulty_level_name":"مبتدئ","difficulty_level":2,"answers_data":[{"answer1":"<p>القصاص</p>\r\n","is_correct":"true"},{"answer2":"<p>الحبس</p>\r\n","is_correct":"false"},{"answer3":"<p>الدية</p>\r\n","is_correct":"false"},{"answer4":"<p>الصلب</p>\r\n","is_correct":"false"}]},{"title":"<p>طبيب حقن مريضا ً بإبرة قاصدا ً علاجه فمات بسببها يتوجب ...</p>\r\n","explain_answer":"","year":2023,"score":2,"article":null,"difficulty_level_name":"مبتدئ","difficulty_level":2,"answers_data":[{"answer1":"<p>القصاص والدية</p>\r\n","is_correct":"false"},{"answer2":"<p>الصلب والدية</p>\r\n","is_correct":"false"},{"answer3":"<p>الدية والجلد</p>\r\n","is_correct":"false"},{"answer4":"<p>الصيام والدية</p>\r\n","is_correct":"true"}]},{"title":"<p>ضرب شخص جاره بعصا غير غليظة تسببت بموته يُعد قتلاً ...</p>\r\n","explain_answer":"","year":2023,"score":2,"article":null,"difficulty_level_name":"مبتدئ","difficulty_level":2,"answers_data":[{"answer1":"<p>عمداً</p>\r\n","is_correct":"false"},{"answer2":"<p>شبه عمد</p>\r\n","is_correct":"true"},{"answer3":"<p>خطأ</p>\r\n","is_correct":"false"},{"answer4":"<p>حرابةً</p>\r\n","is_correct":"false"}]},{"title":"<p>جميع أنواع القتل تثبت بإلاقرار أو الشهادة.</p>\r\n","explain_answer":"","year":2023,"score":1,"article":null,"difficulty_level_name":"مبتدئ","difficulty_level":2,"answers_data":[{"answer1":"<p>صح</p>\r\n","is_correct":"true"},{"answer2":"<p>خطأ</p>\r\n","is_correct":"false"}]},{"title":"<p>يحبس القاتل إذا كان ولي الدم...</p>\r\n","explain_answer":"","year":2022,"score":2,"article":null,"difficulty_level_name":"مبتدئ","difficulty_level":2,"answers_data":[{"answer1":"<p>بالغاً</p>\r\n","is_correct":"false"},{"answer2":"<p>عاقلاً</p>\r\n","is_correct":"false"},{"answer3":"<p>امرأة</p>\r\n","is_correct":"false"},{"answer4":"<p>صغيراً</p>\r\n","is_correct":"true"}]},{"title":"<p>يقيم حد القصاص على القاتل...</p>\r\n","explain_answer":"","year":2022,"score":2,"article":null,"difficulty_level_name":"مبتدئ","difficulty_level":2,"answers_data":[{"answer1":"<p>الأخ</p>\r\n","is_correct":"false"},{"answer2":"<p>الابن</p>\r\n","is_correct":"false"},{"answer3":"<p>الأب</p>\r\n","is_correct":"false"},{"answer4":"<p>القاضي</p>\r\n","is_correct":"true"}]},{"title":"<p>تنازل أولياء الدم عن القصاص يوجب الدية ...</p>\r\n","explain_answer":"<p>تنازل أولياء الدم عن القصاص في القتل العمد يوجب الدية<u> المغلظة المعجلة </u>من مال القاتل، وفي القتل شبه العمد يوجب الدية المخففة المؤجلة وعلى العاقلة.</p>\r\n","year":2023,"score":2,"article":null,"difficulty_level_name":"متوسط","difficulty_level":3,"answers_data":[{"answer1":"<p>المخففة</p>\r\n","is_correct":"false"},{"answer2":"<p>المؤجلة</p>\r\n","is_correct":"false"},{"answer3":"<p>المغلظة</p>\r\n","is_correct":"true"},{"answer4":"<p>على العاقلة</p>\r\n","is_correct":"false"}]},{"title":"حقن طبيب شخصا ً بإبرة عامدا ً قتله فمات يوجب ...","explain_answer":null,"year":2023,"score":2,"article":null,"difficulty_level_name":"مبتدئ","difficulty_level":2,"answers_data":[{"answer1":"القصاص","is_correct":"true"},{"answer2":"الحبس","is_correct":"false"},{"answer3":"الدية","is_correct":"false"},{"answer4":"الصلب","is_correct":"false"}]},{"title":"<p>القتل الخطأ يوجب ...</p>\r\n","explain_answer":"","year":2023,"score":2,"article":null,"difficulty_level_name":"متوسط","difficulty_level":3,"answers_data":[{"answer1":"<p>القصاص</p>\r\n","is_correct":"false"},{"answer2":"<p>الدية المغلظة</p>\r\n","is_correct":"false"},{"answer3":"<p>الدية المعجلة</p>\r\n","is_correct":"false"},{"answer4":"<p>الدية المؤجلة</p>\r\n","is_correct":"true"}]},{"title":"<p>عفو أحد أولياء الدم يسقط عقوبة القصاص.</p>\r\n","explain_answer":"<p><strong>نعم </strong>، عفو أحد أولياء الدم يسقط عقوبة القصاص.</p>\r\n\r\n<p>فمن شروط استيفاء القصاص :</p>\r\n\r\n<p>1- أن يكون ولي الدم بالغاً عاقلاً، فإن كان صغيراً، أو مجنوناً، أو غائباً، حُبس الجاني حتى يبلغ الصغير، ويعقل المجنون، ويقدم الغائب، ثم إن شاء اقتص، أو أخذ الدية، أو عفا وهو الأفضل.</p>\r\n\r\n<p>٢ - اتفاق جميع أولياء الدم على استيفائه، فليس لبعضهم استيفاؤه دون بعض، <strong>وإذا عفا أحد الأولياء سقط القصاص</strong> وتعينت الدية مغلظة.</p>\r\n","year":2023,"score":1,"article":null,"difficulty_level_name":"مبتدئ","difficulty_level":2,"answers_data":[{"answer1":"صح","is_correct":"true"},{"answer2":"خطأ","is_correct":"false"}]},{"title":"يترتب على من قتل شخصا ً أثناء تنظيف سلاحه ...","explain_answer":null,"year":2023,"score":2,"article":null,"difficulty_level_name":"مبتدئ","difficulty_level":2,"answers_data":[{"answer1":"التعزير","is_correct":"false"},{"answer2":"القصاص","is_correct":"false"},{"answer3":"الدية","is_correct":"true"},{"answer4":"الأرش","is_correct":"false"}]},{"title":"<p>يحبس القاتل إذا كان ولي الدم...</p>\r\n","explain_answer":"","year":2022,"score":2,"article":null,"difficulty_level_name":"مبتدئ","difficulty_level":2,"answers_data":[{"answer1":"<p>بالغاً</p>\r\n","is_correct":"false"},{"answer2":"<p>عاقلاً</p>\r\n","is_correct":"false"},{"answer3":"<p>امرأة</p>\r\n","is_correct":"false"},{"answer4":"<p>صغيراً</p>\r\n","is_correct":"true"}]},{"title":"<p>يقيم حد القصاص على القاتل...</p>\r\n","explain_answer":"","year":2022,"score":2,"article":null,"difficulty_level_name":"مبتدئ","difficulty_level":2,"answers_data":[{"answer1":"<p>الأخ</p>\r\n","is_correct":"false"},{"answer2":"<p>الابن</p>\r\n","is_correct":"false"},{"answer3":"<p>الأب</p>\r\n","is_correct":"false"},{"answer4":"<p>القاضي</p>\r\n","is_correct":"true"}]},{"title":"<p>طبيب حقن مريضا ً بإبرة قاصدا ً علاجه فمات بسببها يتوجب ...</p>\r\n","explain_answer":"","year":2023,"score":2,"article":null,"difficulty_level_name":"مبتدئ","difficulty_level":2,"answers_data":[{"answer1":"<p>القصاص والدية</p>\r\n","is_correct":"false"},{"answer2":"<p>الصلب والدية</p>\r\n","is_correct":"false"},{"answer3":"<p>الدية والجلد</p>\r\n","is_correct":"false"},{"answer4":"<p>الصيام والدية</p>\r\n","is_correct":"true"}]},{"title":"<p>يحبس القاتل إذا كان ولي الدم..</p>\r\n","explain_answer":"","year":2022,"score":2,"article":null,"difficulty_level_name":"مبتدئ","difficulty_level":2,"answers_data":[{"answer1":"<p>بالغاً</p>\r\n","is_correct":"false"},{"answer2":"<p>عاقلاً</p>\r\n","is_correct":"false"},{"answer3":"<p>امرأةً</p>\r\n","is_correct":"false"},{"answer4":"<p>صغيراً</p>\r\n","is_correct":"true"}]},{"title":"<p>يقيم حد القصاص على القاتل...</p>\r\n","explain_answer":"","year":2022,"score":2,"article":null,"difficulty_level_name":"مبتدئ","difficulty_level":2,"answers_data":[{"answer1":"<p>الأخ</p>\r\n","is_correct":"false"},{"answer2":"<p>الابن</p>\r\n","is_correct":"false"},{"answer3":"<p>الأب</p>\r\n","is_correct":"false"},{"answer4":"<p>القاضي</p>\r\n","is_correct":"true"}]},{"title":"<p>عد الإسلام قتل النفس من ...</p>\r\n","explain_answer":"","year":2023,"score":2,"article":null,"difficulty_level_name":"مبتدئ","difficulty_level":2,"answers_data":[{"answer1":"<p>الكبائر</p>\r\n","is_correct":"true"},{"answer2":"<p>الشرك</p>\r\n","is_correct":"false"},{"answer3":"<p>الرياء</p>\r\n","is_correct":"false"},{"answer4":"<p>المحقرات</p>\r\n","is_correct":"false"}]},{"title":"<p>قيام المكلف بإزهاق روح مسلم معصوم الدم بآلة من شأنها القتل غالبا ً يعد ...</p>\r\n","explain_answer":"","year":2023,"score":2,"article":null,"difficulty_level_name":"مبتدئ","difficulty_level":2,"answers_data":[{"answer1":"<p>قتلاً عمداً</p>\r\n","is_correct":"true"},{"answer2":"<p>قتلاً خطأ</p>\r\n","is_correct":"false"},{"answer3":"<p>قتلاً شبه عمداً</p>\r\n","is_correct":"false"},{"answer4":"<p>حرابة</p>\r\n","is_correct":"false"}]},{"title":"<p>عفو أحد أولياء الدم عن القاتل يوجب ...</p>\r\n","explain_answer":"<p><strong>نعم </strong>، عفو أحد أولياء الدم يسقط عقوبة القصاص <strong>ويوجب الديه</strong> .</p>\r\n\r\n<p>فمن شروط استيفاء القصاص :</p>\r\n\r\n<p>1- أن يكون ولي الدم بالغاً عاقلاً، فإن كان صغيراً، أو مجنوناً، أو غائباً، حُبس الجاني حتى يبلغ الصغير، ويعقل المجنون، ويقدم الغائب، ثم إن شاء اقتص، أو أخذ الدية، أو عفا وهو الأفضل.</p>\r\n\r\n<p>٢ - اتفاق جميع أولياء الدم على استيفائه، فليس لبعضهم استيفاؤه دون بعض، <strong>وإذا عفا أحد الأولياء سقط القصاص</strong> وتعينت <strong>الدية </strong>مغلظة.</p>\r\n","year":2023,"score":2,"article":null,"difficulty_level_name":"مبتدئ","difficulty_level":2,"answers_data":[{"answer1":"<p>القصاص</p>\r\n","is_correct":"false"},{"answer2":"<p>الدية</p>\r\n","is_correct":"true"},{"answer3":"<p>الحبس</p>\r\n","is_correct":"false"},{"answer4":"<p>الجلد</p>\r\n","is_correct":"false"}]},{"title":"<p>يحبس القاتل اذا كان ولي الدم ...</p>\r\n","explain_answer":"","year":2023,"score":2,"article":null,"difficulty_level_name":"مبتدئ","difficulty_level":2,"answers_data":[{"answer1":"<p>بالغاً</p>\r\n","is_correct":"false"},{"answer2":"<p>عاقلاً</p>\r\n","is_correct":"false"},{"answer3":"<p>مختاراً</p>\r\n","is_correct":"false"},{"answer4":"<p>غائباً</p>\r\n","is_correct":"true"}]}],"scope":"lesson"}]